odoo/addons/account_multicompany_easy_creation/README.rst
odoo/addons/account_multicompany_easy_creation/__init__.py
odoo/addons/account_multicompany_easy_creation/__manifest__.py
odoo/addons/account_multicompany_easy_creation/i18n/account_multicompany_easy_creation.pot
odoo/addons/account_multicompany_easy_creation/i18n/es.po
odoo/addons/account_multicompany_easy_creation/i18n/pt.po
odoo/addons/account_multicompany_easy_creation/readme/CONTRIBUTORS.rst
odoo/addons/account_multicompany_easy_creation/readme/DESCRIPTION.rst
odoo/addons/account_multicompany_easy_creation/readme/USAGE.rst
odoo/addons/account_multicompany_easy_creation/static/description/icon.png
odoo/addons/account_multicompany_easy_creation/static/description/index.html
odoo/addons/account_multicompany_easy_creation/tests/__init__.py
odoo/addons/account_multicompany_easy_creation/tests/test_easy_creation.py
odoo/addons/account_multicompany_easy_creation/wizards/__init__.py
odoo/addons/account_multicompany_easy_creation/wizards/multicompany_easy_creation.py
odoo/addons/account_multicompany_easy_creation/wizards/multicompany_easy_creation.xml
odoo12_addon_account_multicompany_easy_creation-12.0.1.0.1.dist-info/METADATA
odoo12_addon_account_multicompany_easy_creation-12.0.1.0.1.dist-info/WHEEL
odoo12_addon_account_multicompany_easy_creation-12.0.1.0.1.dist-info/top_level.txt
odoo12_addon_account_multicompany_easy_creation-12.0.1.0.1.dist-info/RECORD
